yugam_sharma/__init__.py
yugam_sharma/__main__.py
yugam_sharma/names.txt
yugam_sharma/speaker.py
yugam_sharma/speakers/__init__.py
yugam_sharma/speakers/yugam.py
yugam_sharma-0.3.0.dist-info/licenses/LICENSE.txt
yugam_sharma-0.3.0.dist-info/METADATA
yugam_sharma-0.3.0.dist-info/WHEEL
yugam_sharma-0.3.0.dist-info/entry_points.txt
yugam_sharma-0.3.0.dist-info/top_level.txt
yugam_sharma-0.3.0.dist-info/RECORD
