Metadata-Version: 2.4
Name: yugam_sharma
Version: 0.3.0
Summary: My first package!
Author-email: Yugam Sharma <yugam.sharma@yahoo.com>
Maintainer-email: Yugam Sharma <yugam.sharma@yahoo.com>
License: Copyright 2025 Yugam Sharma
Project-URL: Homepage, https://github.com/ysharma-dev/yugam_sharma
Project-URL: Documentation, https://github.com/ysharma-dev/yugam_sharma/README.md
Keywords: Sharma
Classifier: Programming Language :: Python :: 3.13
Classifier: Programming Language :: Python :: Implementation :: CPython
Classifier: License :: OSI Approved :: BSD License
Classifier: Intended Audience :: Developers
Classifier: Operating System :: POSIX :: Linux
Classifier: Operating System :: Microsoft :: Windows
Classifier: Operating System :: MacOS
Classifier: Operating System :: MacOS :: MacOS X
Requires-Python: >=3.13
License-File: LICENSE.txt
Requires-Dist: colorama~=0.0
Provides-Extra: dev
Requires-Dist: twine; extra == "dev"
Requires-Dist: build; extra == "dev"
Dynamic: license-file
